dewi_core/__init__.py
dewi_core/appcontext.py
dewi_core/application.py
dewi_core/command.py
dewi_core/commandplugin.py
dewi_core/commandregistry.py
dewi_core/config_env.py
dewi_core/context_managers.py
dewi_core/logger.py
dewi_core/optioncontext.py
dewi_core/remoting.py
dewi_core/testcase.py
dewi_core/commands/__init__.py
dewi_core/commands/edit/__init__.py
dewi_core/commands/edit/__main__.py
dewi_core/commands/edit/edit.py
dewi_core/commands/editreview/__init__.py
dewi_core/commands/editreview/__main__.py
dewi_core/commands/review/__init__.py
dewi_core/commands/review/__main__.py
dewi_core/commands/review/commands.py
dewi_core/config/__init__.py
dewi_core/config/appconfig.py
dewi_core/config/config.py
dewi_core/config/iniconfig.py
dewi_core/config/node.py
dewi_core/loader/__init__.py
dewi_core/loader/context.py
dewi_core/loader/loader.py
dewi_core/loader/plugin.py
dewi_core/projects/__init__.py
dewi_core/utils/__init__.py
dewi_core/utils/dictionaries.py
dewi_core/utils/exception.py
dewi_core/utils/files.py
dewi_core/utils/levenshtein.py
dewi_core/utils/log_dict.py
dewi_core/utils/man.py
dewi_core/utils/time.py
dewi_core/utils/yaml.py
dewi_core-5.4.0.dist-info/COPYING
dewi_core-5.4.0.dist-info/METADATA
dewi_core-5.4.0.dist-info/WHEEL
dewi_core-5.4.0.dist-info/top_level.txt
dewi_core-5.4.0.dist-info/zip-safe
dewi_core-5.4.0.dist-info/RECORD
