Metadata-Version: 2.1
Name: dewi-core
Version: 5.4.0
Summary: DEWI Core: Plugin and Config Tree framework and Application
Home-page: https://github.com/LA-Toth/dewi_core
Author: Laszlo Attila Toth
Author-email: python-dewi@laszloattilatoth.me
Maintainer: Laszlo Attila Toth
Maintainer-email: python-dewi@laszloattilatoth.me
License: Apache
Keywords: tool framework development synchronization
Platform: UNKNOWN
Classifier: Development Status :: 5 - Production/Stable
Classifier: Environment :: Console
Classifier: Intended Audience :: Developers
Classifier: License :: OSI Approved :: Apache Software License
Classifier: Natural Language :: English
Classifier: Operating System :: POSIX
Classifier: Operating System :: POSIX :: Linux
Classifier: Operating System :: MacOS :: MacOS X
Classifier: Operating System :: Microsoft :: Windows
Classifier: Programming Language :: Python
Classifier: Programming Language :: Python :: 3 :: Only
Classifier: Programming Language :: Python :: 3.10
Classifier: Programming Language :: Python :: 3.11
Classifier: Topic :: Software Development
Classifier: Topic :: Software Development :: Libraries
Classifier: Topic :: Software Development :: Libraries :: Application Frameworks
Classifier: Topic :: Utilities
Requires-Python: >=3.10
License-File: COPYING
Requires-Dist: click (<9,>=8.0)
Requires-Dist: click-option-group
Requires-Dist: pyyaml
